Pairwise.py
Taxon.py
Timeline.py
timetree.py
timetreeapi-0.1.0.dist-info/LICENSE
timetreeapi-0.1.0.dist-info/METADATA
timetreeapi-0.1.0.dist-info/WHEEL
timetreeapi-0.1.0.dist-info/top_level.txt
timetreeapi-0.1.0.dist-info/RECORD
