Metadata-Version: 2.1
Name: timetreeapi
Version: 0.1.0
Summary: Add your description here
Requires-Python: >=3.12
License-File: LICENSE
Requires-Dist: autopep8>=2.3.1
Requires-Dist: pandas>=2.2.3
Requires-Dist: pylint>=3.3.1
Requires-Dist: requests>=2.32.3
Requires-Dist: tool>=0.8.0
